{
  "name": "Mihir Pathak",
  "title": "Full Stack Developer",
  "url": "htts://mihirpathak.in",
  "social": [
    {
      "type": "E-mail",
      "username": "mihirpathak97@gmail.com",
      "url": "mailto:mihirpathak97@gmail.com",
      "icon": "mail"
    },
    {
      "type": "GitHub",
      "username": "mihirpathak97",
      "url": "https://github.com/mihirpathak97",
      "icon": "github"
    },
    {
      "type": "LinkedIn",
      "username": "in/mihirpathak97",
      "url": "https://linkedin.com/in/mihirpathak97",
      "icon": "linkedin"
    },
    {
      "type": "Twitter",
      "username": "mihirpathak97",
      "url": "https://twitter.com/mihirpathak97",
      "icon": "twitter"
    },
    {
      "type": "Facebook",
      "username": "mihirpathak97",
      "url": "https://facebook.com/mihirpathak97",
      "icon": "facebook"
    },
    {
      "type": "Instagram",
      "username": "the_indian_engineer",
      "url": "https://instagram.com/the_indian_engineer",
      "icon": "instagram"
    }
  ]
}